{
    "apiVersion": 1.2,
    "id": 1,
    "plans": [
        {
            "agentInitPos": [
                {
                    "x": -100,
                    "y": -100
                },
                {
                    "x": 5.0718232044198892,
                    "y": -3.9487500000000004
                },
                {
                    "x": 4.7624309392265189,
                    "y": -4.0724999999999998
                },
                {
                    "x": 5.3259668508287294,
                    "y": -3.6337500000000009
                },
                {
                    "x": 5.2486187845303878,
                    "y": -4.1850000000000005
                },
                {
                    "x": 4.5414364640883971,
                    "y": -4.1737500000000001
                },
                {
                    "x": 5.5580110497237563,
                    "y": -3.3075000000000001
                },
                {
                    "x": 4.1988950276243102,
                    "y": -4.1962500000000009
                }
            ],
            "agents": [
                {
                    "ID": 0,
                    "positions": [
                        {
                            "angel": -121.37300514010845,
                            "pos-x": 5.6022099447513813,
                            "pos-y": -4.0274999999999999,
                            "skills": [
                                {
                                    "flag": false,
                                    "name": "MoveSkill",
                                    "primary": 0,
                                    "secondary": 0
                                },
                                {
                                    "flag": false,
                                    "name": "PassSkill",
                                    "primary": 500,
                                    "secondary": 500,
                                    "target": {
                                        "agent": 1,
                                        "index": 2
                                    }
                                }
                            ],
                            "tolerance": 30
                        },
                        {
                            "angel": 0,
                            "pos-x": 1.4143646408839778,
                            "pos-y": -3.7800000000000011,
                            "skills": [
                                {
                                    "flag": false,
                                    "name": "MoveSkill",
                                    "primary": 0,
                                    "secondary": 0
                                }
                            ],
                            "tolerance": 30
                        },
                        {
                            "angel": 0,
                            "pos-x": 3.6574585635359114,
                            "pos-y": -1.6200000000000001,
                            "skills": [
                                {
                                    "flag": false,
                                    "name": "MoveSkill",
                                    "primary": 0,
                                    "secondary": 0
                                }
                            ],
                            "tolerance": 30
                        }
                    ]
                },
                {
                    "ID": 1,
                    "positions": [
                        {
                            "angel": 77.905242922987895,
                            "pos-x": 5.0718232044198892,
                            "pos-y": -3.9487500000000004,
                            "skills": [
                                {
                                    "flag": false,
                                    "name": "MoveSkill",
                                    "primary": 0,
                                    "secondary": 0
                                }
                            ],
                            "tolerance": 30
                        },
                        {
                            "angel": 75.963756532073532,
                            "pos-x": 4.1215469613259668,
                            "pos-y": 1.5524999999999998,
                            "skills": [
                                {
                                    "flag": false,
                                    "name": "MoveSkill",
                                    "primary": 0,
                                    "secondary": 0
                                }
                            ],
                            "tolerance": 30
                        },
                        {
                            "angel": 78.996459148250509,
                            "pos-x": 4.5635359116022087,
                            "pos-y": 1.8337499999999998,
                            "skills": [
                                {
                                    "flag": false,
                                    "name": "MoveSkill",
                                    "primary": 0,
                                    "secondary": 0
                                },
                                {
                                    "flag": false,
                                    "name": "OneTouchSkill",
                                    "primary": 500,
                                    "secondary": 200
                                }
                            ],
                            "tolerance": 30
                        },
                        {
                            "angel": 0,
                            "pos-x": 3.8453038674033149,
                            "pos-y": 3.65625,
                            "skills": [
                                {
                                    "flag": false,
                                    "name": "MoveSkill",
                                    "primary": 0,
                                    "secondary": 0
                                }
                            ],
                            "tolerance": 30
                        }
                    ]
                },
                {
                    "ID": 2,
                    "positions": [
                        {
                            "angel": 0,
                            "pos-x": 4.7624309392265189,
                            "pos-y": -4.0724999999999998,
                            "skills": [
                                {
                                    "flag": false,
                                    "name": "MoveSkill",
                                    "primary": 0,
                                    "secondary": 0
                                }
                            ],
                            "tolerance": 30
                        },
                        {
                            "angel": 0,
                            "pos-x": 2.9392265193370175,
                            "pos-y": -0.58499999999999908,
                            "skills": [
                                {
                                    "flag": false,
                                    "name": "MoveSkill",
                                    "primary": 0,
                                    "secondary": 0
                                }
                            ],
                            "tolerance": 30
                        },
                        {
                            "angel": 0,
                            "pos-x": 3.7127071823204414,
                            "pos-y": -1.1362499999999995,
                            "skills": [
                                {
                                    "flag": false,
                                    "name": "MoveSkill",
                                    "primary": 0,
                                    "secondary": 0
                                }
                            ],
                            "tolerance": 30
                        },
                        {
                            "angel": 0,
                            "pos-x": 3.3922651933701662,
                            "pos-y": 0.12375000000000025,
                            "skills": [
                                {
                                    "flag": false,
                                    "name": "MoveSkill",
                                    "primary": 0,
                                    "secondary": 0
                                },
                                {
                                    "flag": false,
                                    "name": "Mark",
                                    "primary": 500,
                                    "secondary": 500
                                }
                            ],
                            "tolerance": 30
                        }
                    ]
                },
                {
                    "ID": 3,
                    "positions": [
                        {
                            "angel": 0,
                            "pos-x": 5.3259668508287294,
                            "pos-y": -3.6337500000000009,
                            "skills": [
                                {
                                    "flag": false,
                                    "name": "MoveSkill",
                                    "primary": 0,
                                    "secondary": 0
                                }
                            ],
                            "tolerance": 30
                        },
                        {
                            "angel": 0,
                            "pos-x": 2.4972375690607738,
                            "pos-y": -2.7450000000000001,
                            "skills": [
                                {
                                    "flag": false,
                                    "name": "MoveSkill",
                                    "primary": 0,
                                    "secondary": 0
                                }
                            ],
                            "tolerance": 30
                        },
                        {
                            "angel": 0,
                            "pos-x": 2.4419889502762437,
                            "pos-y": -1.2824999999999998,
                            "skills": [
                                {
                                    "flag": false,
                                    "name": "MoveSkill",
                                    "primary": 0,
                                    "secondary": 0
                                }
                            ],
                            "tolerance": 30
                        },
                        {
                            "angel": 0,
                            "pos-x": 3.1049723756906076,
                            "pos-y": 0.70874999999999977,
                            "skills": [
                                {
                                    "flag": false,
                                    "name": "MoveSkill",
                                    "primary": 0,
                                    "secondary": 0
                                },
                                {
                                    "flag": false,
                                    "name": "Mark",
                                    "primary": 500,
                                    "secondary": 500
                                }
                            ],
                            "tolerance": 30
                        }
                    ]
                },
                {
                    "ID": 4,
                    "positions": [
                        {
                            "angel": 0,
                            "pos-x": 5.2486187845303878,
                            "pos-y": -4.1850000000000005,
                            "skills": [
                                {
                                    "flag": false,
                                    "name": "MoveSkill",
                                    "primary": 0,
                                    "secondary": 0
                                }
                            ],
                            "tolerance": 30
                        },
                        {
                            "angel": 33.178511659392747,
                            "pos-x": 2.5414364640883988,
                            "pos-y": 2.2275,
                            "skills": [
                                {
                                    "flag": false,
                                    "name": "MoveSkill",
                                    "primary": 0,
                                    "secondary": 0
                                }
                            ],
                            "tolerance": 30
                        },
                        {
                            "angel": 64.592281891051528,
                            "pos-x": 3.4143646408839778,
                            "pos-y": 2.8912500000000003,
                            "skills": [
                                {
                                    "flag": false,
                                    "name": "MoveSkill",
                                    "primary": 0,
                                    "secondary": 0
                                },
                                {
                                    "flag": false,
                                    "name": "OneTouchSkill",
                                    "primary": 500,
                                    "secondary": 300
                                }
                            ],
                            "tolerance": 50
                        },
                        {
                            "angel": 0,
                            "pos-x": 3.4475138121546962,
                            "pos-y": 1.1699999999999999,
                            "skills": [
                                {
                                    "flag": false,
                                    "name": "MoveSkill",
                                    "primary": 0,
                                    "secondary": 0
                                },
                                {
                                    "flag": false,
                                    "name": "Mark",
                                    "primary": 500,
                                    "secondary": 300
                                }
                            ],
                            "tolerance": 30
                        }
                    ]
                },
                {
                    "ID": 5,
                    "positions": [
                        {
                            "angel": 0,
                            "pos-x": 4.5414364640883971,
                            "pos-y": -4.1737500000000001,
                            "skills": [
                                {
                                    "flag": false,
                                    "name": "MoveSkill",
                                    "primary": 0,
                                    "secondary": 0
                                }
                            ],
                            "tolerance": 30
                        },
                        {
                            "angel": 0,
                            "pos-x": 2.1767955801104968,
                            "pos-y": 0.40500000000000025,
                            "skills": [
                                {
                                    "flag": false,
                                    "name": "MoveSkill",
                                    "primary": 0,
                                    "secondary": 0
                                }
                            ],
                            "tolerance": 30
                        },
                        {
                            "angel": 0,
                            "pos-x": 0.57458563535911544,
                            "pos-y": 3.0374999999999996,
                            "skills": [
                                {
                                    "flag": false,
                                    "name": "MoveSkill",
                                    "primary": 0,
                                    "secondary": 0
                                }
                            ],
                            "tolerance": 30
                        },
                        {
                            "angel": 0,
                            "pos-x": 2.1104972375690618,
                            "pos-y": 3.1387499999999999,
                            "skills": [
                                {
                                    "flag": false,
                                    "name": "MoveSkill",
                                    "primary": 0,
                                    "secondary": 0
                                }
                            ],
                            "tolerance": 30
                        },
                        {
                            "angel": 0,
                            "pos-x": 1.6906077348066297,
                            "pos-y": -2.4862500000000001,
                            "skills": [
                                {
                                    "flag": false,
                                    "name": "MoveSkill",
                                    "primary": 0,
                                    "secondary": 0
                                }
                            ],
                            "tolerance": 30
                        },
                        {
                            "angel": 0,
                            "pos-x": 1.193370165745856,
                            "pos-y": -3.2850000000000001,
                            "skills": [
                                {
                                    "flag": false,
                                    "name": "MoveSkill",
                                    "primary": 0,
                                    "secondary": 0
                                }
                            ],
                            "tolerance": 30
                        }
                    ]
                },
                {
                    "ID": 6,
                    "positions": [
                        {
                            "angel": 0,
                            "pos-x": 5.5580110497237563,
                            "pos-y": -3.3075000000000001,
                            "skills": [
                                {
                                    "flag": false,
                                    "name": "MoveSkill",
                                    "primary": 0,
                                    "secondary": 0
                                }
                            ],
                            "tolerance": 30
                        },
                        {
                            "angel": 0,
                            "pos-x": 1.1270718232044192,
                            "pos-y": -1.4400000000000004,
                            "skills": [
                                {
                                    "flag": false,
                                    "name": "MoveSkill",
                                    "primary": 0,
                                    "secondary": 0
                                }
                            ],
                            "tolerance": 30
                        },
                        {
                            "angel": 0,
                            "pos-x": 1.303867403314916,
                            "pos-y": 3.2512499999999998,
                            "skills": [
                                {
                                    "flag": false,
                                    "name": "MoveSkill",
                                    "primary": 0,
                                    "secondary": 0
                                }
                            ],
                            "tolerance": 30
                        },
                        {
                            "angel": 0,
                            "pos-x": 0.35359116022099535,
                            "pos-y": 1.3387500000000001,
                            "skills": [
                                {
                                    "flag": false,
                                    "name": "MoveSkill",
                                    "primary": 0,
                                    "secondary": 0
                                }
                            ],
                            "tolerance": 30
                        },
                        {
                            "angel": 0,
                            "pos-x": 0.34254143646408863,
                            "pos-y": 0.13499999999999979,
                            "skills": [
                                {
                                    "flag": false,
                                    "name": "MoveSkill",
                                    "primary": 0,
                                    "secondary": 0
                                }
                            ],
                            "tolerance": 30
                        }
                    ]
                },
                {
                    "ID": 7,
                    "positions": [
                        {
                            "angel": 0,
                            "pos-x": 4.1988950276243102,
                            "pos-y": -4.1962500000000009,
                            "skills": [
                                {
                                    "flag": false,
                                    "name": "MoveSkill",
                                    "primary": 0,
                                    "secondary": 0
                                }
                            ],
                            "tolerance": 30
                        },
                        {
                            "angel": 0,
                            "pos-x": 4.2320441988950286,
                            "pos-y": 3.4537499999999999,
                            "skills": [
                                {
                                    "flag": false,
                                    "name": "MoveSkill",
                                    "primary": 0,
                                    "secondary": 0
                                }
                            ],
                            "tolerance": 30
                        },
                        {
                            "angel": 77.471192290848492,
                            "pos-x": 4.7845303867403324,
                            "pos-y": 3.4312500000000004,
                            "skills": [
                                {
                                    "flag": false,
                                    "name": "MoveSkill",
                                    "primary": 0,
                                    "secondary": 0
                                },
                                {
                                    "flag": false,
                                    "name": "OneTouchSkill",
                                    "primary": 500,
                                    "secondary": 200
                                }
                            ],
                            "tolerance": 50
                        },
                        {
                            "angel": 0,
                            "pos-x": 1.8674033149171265,
                            "pos-y": 3.8250000000000002,
                            "skills": [
                                {
                                    "flag": false,
                                    "name": "MoveSkill",
                                    "primary": 0,
                                    "secondary": 0
                                }
                            ],
                            "tolerance": 30
                        }
                    ]
                }
            ],
            "ballInitPos": {
                "x": 5.6022099447513813,
                "y": -4.0274999999999999
            },
            "chance": 1,
            "lastDist": 1.5,
            "maxEffective": 2,
            "minNeeded": 2,
            "planMode": "INDIRECT",
            "tags": [
                ""
            ]
        }
    ]
}
