{
    "apiVersion": 1.2,
    "id": 1,
    "plans": [
        {
            "agentInitPos": [
                {
                    "x": -100,
                    "y": -100
                },
                {
                    "x": 3.0704573547589615,
                    "y": -2.3782894736842106
                },
                {
                    "x": 2.4029666254635353,
                    "y": -2.5855263157894735
                }
            ],
            "agents": [
                {
                    "ID": 0,
                    "positions": [
                        {
                            "angel": 0,
                            "pos-x": 3.8046971569839307,
                            "pos-y": -2.338815789473684,
                            "skills": [
                                {
                                    "flag": false,
                                    "name": "MoveSkill",
                                    "primary": 0,
                                    "secondary": 0
                                },
                                {
                                    "flag": false,
                                    "name": "PassSkill",
                                    "primary": -1,
                                    "secondary": 350,
                                    "target": {
                                        "agent": 1,
                                        "index": 2
                                    }
                                }
                            ],
                            "tolerance": 30
                        },
                        {
                            "angel": 0,
                            "pos-x": 2.6588380716934488,
                            "pos-y": -1.075657894736842,
                            "skills": [
                                {
                                    "flag": false,
                                    "name": "MoveSkill",
                                    "primary": 0,
                                    "secondary": 0
                                }
                            ],
                            "tolerance": 30
                        }
                    ]
                },
                {
                    "ID": 1,
                    "positions": [
                        {
                            "angel": 0,
                            "pos-x": 3.0704573547589615,
                            "pos-y": -2.3782894736842106,
                            "skills": [
                                {
                                    "flag": false,
                                    "name": "MoveSkill",
                                    "primary": 0,
                                    "secondary": 0
                                }
                            ],
                            "tolerance": 30
                        },
                        {
                            "angel": 0,
                            "pos-x": 0.10012360939431397,
                            "pos-y": 1.805921052631579,
                            "skills": [
                                {
                                    "flag": false,
                                    "name": "MoveSkill",
                                    "primary": 0,
                                    "secondary": 0
                                }
                            ],
                            "tolerance": 30
                        },
                        {
                            "angel": 0,
                            "pos-x": 3.248454882571075,
                            "pos-y": 1.8355263157894735,
                            "skills": [
                                {
                                    "flag": false,
                                    "name": "MoveSkill",
                                    "primary": 0,
                                    "secondary": 0
                                },
                                {
                                    "flag": false,
                                    "name": "OneTouchSkill",
                                    "primary": 850,
                                    "secondary": 800
                                }
                            ],
                            "tolerance": 30
                        }
                    ]
                },
                {
                    "ID": 2,
                    "positions": [
                        {
                            "angel": 0,
                            "pos-x": 2.4029666254635353,
                            "pos-y": -2.5855263157894735,
                            "skills": [
                                {
                                    "flag": false,
                                    "name": "MoveSkill",
                                    "primary": 0,
                                    "secondary": 0
                                }
                            ],
                            "tolerance": 30
                        },
                        {
                            "angel": 0,
                            "pos-x": 0.934487021013597,
                            "pos-y": -1.944078947368421,
                            "skills": [
                                {
                                    "flag": false,
                                    "name": "MoveSkill",
                                    "primary": 0,
                                    "secondary": 0
                                }
                            ],
                            "tolerance": 30
                        },
                        {
                            "angel": 0,
                            "pos-x": 0.8343634116192831,
                            "pos-y": 2.3782894736842106,
                            "skills": [
                                {
                                    "flag": false,
                                    "name": "MoveSkill",
                                    "primary": 0,
                                    "secondary": 0
                                }
                            ],
                            "tolerance": 30
                        },
                        {
                            "angel": 0,
                            "pos-x": 3.7713226205191597,
                            "pos-y": 2.1217105263157894,
                            "skills": [
                                {
                                    "flag": false,
                                    "name": "MoveSkill",
                                    "primary": 0,
                                    "secondary": 0
                                },
                                {
                                    "flag": false,
                                    "name": "OneTouchSkill",
                                    "primary": 1000,
                                    "secondary": 600
                                }
                            ],
                            "tolerance": 30
                        }
                    ]
                }
            ],
            "ballInitPos": {
                "x": 3.8046971569839307,
                "y": -2.338815789473684
            },
            "chance": 1,
            "lastDist": 2.700000000000001,
            "planMode": "INDIRECT",
            "tags": [
                ""
            ]
        }
    ]
}
